flows_put_lines-1.0.0.dist-info/licenses/LICENSE
src/__init__.py
src/config.py
src/flows_kpi.py
src/gtfs_extractor.py
src/main.py
src/map_generator.py
src/route_matcher.py
flows_put_lines-1.0.0.dist-info/METADATA
flows_put_lines-1.0.0.dist-info/WHEEL
flows_put_lines-1.0.0.dist-info/entry_points.txt
flows_put_lines-1.0.0.dist-info/top_level.txt
flows_put_lines-1.0.0.dist-info/RECORD
