Metadata-Version: 2.4
Name: flows-put-lines
Version: 1.0.0
Summary: Provision PTV Flows KPIs from GTFS static feeds for entire transit lines
Author-email: PTV Group <luca.paone@ptvgroup.com>
License: MIT
Project-URL: Homepage, https://github.com/lucapaone-ptvgroup/Flows-put-lines
Project-URL: Repository, https://github.com/lucapaone-ptvgroup/Flows-put-lines
Keywords: gtfs,transit,flows,kpi,ptv
Classifier: Development Status :: 4 - Beta
Classifier: Intended Audience :: Developers
Classifier: Topic :: Software Development :: Libraries :: Python Modules
Classifier: Programming Language :: Python :: 3
Classifier: Programming Language :: Python :: 3.10
Classifier: Programming Language :: Python :: 3.11
Classifier: Programming Language :: Python :: 3.12
Requires-Python: >=3.10
License-File: LICENSE
Requires-Dist: pandas>=2.2.0
Requires-Dist: requests>=2.31.0
Requires-Dist: PyYAML>=6.0
Provides-Extra: dev
Requires-Dist: pytest>=7.0; extra == "dev"
Requires-Dist: black>=23.0; extra == "dev"
Requires-Dist: mypy>=1.0; extra == "dev"
Dynamic: license-file
